MANIFEST.in
setup.cfg
setup.py
hncforms/__init__.py
hncforms/formfields.py
hncforms/handlers.py
hncforms/messages.py
hncforms/validators.py
hncforms.egg-info/PKG-INFO
hncforms.egg-info/SOURCES.txt
hncforms.egg-info/dependency_links.txt
hncforms.egg-info/entry_points.txt
hncforms.egg-info/requires.txt
hncforms.egg-info/top_level.txt
hncforms.egg-info/zip-safe
hncforms/templates/approx_field.html
hncforms/templates/basefield.html
hncforms/templates/baseform.html
hncforms/templates/checkbox.html
hncforms/templates/checkbox_post.html
hncforms/templates/combined.html
hncforms/templates/dropdown.html
hncforms/templates/dropdown_multi.html
hncforms/templates/heading.html
hncforms/templates/lib.html
hncforms/templates/picture_upload.html
hncforms/templates/radioselect.html
hncforms/templates/repeatableform.html
hncforms/templates/tagsearch.html
hncforms/templates/textarea.html
hncforms/templates/typeahead.html
hncforms/templates/typeahead_config.html
hncforms/templates/typeahead_token.html