Metadata-Version: 1.0
Name: hncforms
Version: 0.1.6dev
Summary: Form Lib for HnC
Home-page: http://www.hackandcraft.com
Author: Martin Peschke
Author-email: martin@hackandcraft.com
License: UNKNOWN
Keywords: formlib
Platform: UNKNOWN
